my_linode_beatzaplenty/__init__.py
my_linode_beatzaplenty/attach_volume.py
my_linode_beatzaplenty/create_linode_instance.py
my_linode_beatzaplenty/detach_all_volumes.py
my_linode_beatzaplenty/get_firewall_id_by_label.py
my_linode_beatzaplenty/get_ssh_key_id_by_label.py
my_linode_beatzaplenty/get_stackscript_id_by_label_and_username.py
my_linode_beatzaplenty/get_type_label.py
my_linode_beatzaplenty/rename_linode_instance.py
my_linode_beatzaplenty/swap_ipv4_addresses.py
my_linode_beatzaplenty/wait_for_completion.py
my_linode_beatzaplenty/wait_for_instance_state.py
my_linode_beatzaplenty-0.0.3.dist-info/METADATA
my_linode_beatzaplenty-0.0.3.dist-info/WHEEL
my_linode_beatzaplenty-0.0.3.dist-info/licenses/LICENSE
my_linode_beatzaplenty-0.0.3.dist-info/RECORD
