Metadata-Version: 2.1
Name: my_linode_beatzaplenty
Version: 0.0.3
Summary: My Custom linode functions that I use all the time
Project-URL: Homepage, https://github.com/WayneBennett666/linode
Project-URL: Issues, https://github.com/WayneBennett666/linode/issues
Author-email: Wayne Bennett <wayne.bennett@live.com>
License-File: LICENSE
Classifier: License :: OSI Approved :: MIT License
Classifier: Operating System :: OS Independent
Classifier: Programming Language :: Python :: 3
Requires-Python: >=3.8
